sim/counter.sv
// ─── Counter ─────────────────────────────────────────────────────
// WIDTH ビット幅の同期カウンター（非同期アクティブローリセット付き）
// sim/counter.sv と同一コード
// ─────────────────────────────────────────────────────────────────
module counter #(
  parameter WIDTH = 8
)(
  input  wire             clk,
  input  wire             rst_n,
  output reg  [WIDTH-1:0] count
);

  always @(posedge clk or negedge rst_n) begin
    if (!rst_n) begin
      count <= '0;
    end else begin
      count <= count + 1;
    end
  end

endmodule

sim/counter_tb.sv
`timescale 1ns/1ps
// ─── Counter テストベンチ ──────────────────────────────────────────
// VCD ファイルを生成してシミュレーション波形を保存する。
//
// シミュレーション手順:
//   iverilog -g2012 -o counter_sim counter_tb.sv counter.sv
//   vvp counter_sim
//   → counter.vcd が生成される
// ───────────────────────────────────────────────────────────────────
module counter_tb;

  // ─── 信号 ────────────────────────────────────────────────────────
  logic       clk   = 1'b0;
  logic       rst_n = 1'b0;
  logic [7:0] count;

  // ─── DUT インスタンス ────────────────────────────────────────────
  counter #(.WIDTH(8)) u_counter (
    .clk  (clk),
    .rst_n(rst_n),
    .count(count)
  );

  // ─── クロック生成（10 ns 周期 / 100 MHz 相当）───────────────────
  always #5 clk = ~clk;

  // ─── テストシーケンス ─────────────────────────────────────────────
  initial begin
    $dumpfile("counter.vcd");
    $dumpvars(0, counter_tb);

    // ── リセット（3 サイクル）──────────────────────────────────────
    rst_n = 1'b0;
    repeat(3) @(posedge clk);
    #1 rst_n = 1'b1;     // クロック立上り直後に解除（セットアップ余裕あり）

    // ── カウントアップ（20 サイクル）──────────────────────────────
    repeat(20) @(posedge clk);

    // ── リセット再印加（2 サイクル）──────────────────────────────
    #1 rst_n = 1'b0;
    repeat(2) @(posedge clk);
    #1 rst_n = 1'b1;

    // ── 残り 10 サイクル ──────────────────────────────────────────
    repeat(10) @(posedge clk);

    #1 $finish;
  end

  // ─── モニタ（シミュレーションログ）──────────────────────────────
  initial begin
    $monitor("t=%0t  rst_n=%b  count=%0d", $time, rst_n, count);
  end

endmodule

web/public/sample/counter.vcd
$date
	Mon Jun  1 23:11:16 2026
$end
$version
	Icarus Verilog
$end
$timescale
	1ps
$end
$scope module counter_tb $end
$var wire 8 ! count [7:0] $end
$var reg 1 " clk $end
$var reg 1 # rst_n $end
$scope module u_counter $end
$var wire 1 " clk $end
$var wire 1 # rst_n $end
$var reg 8 $ count [7:0] $end
$upscope $end
$upscope $end
$enddefinitions $end
#0
$dumpvars
bx $
0#
0"
bx !
$end
#5000
b0 !
b0 $
1"
#10000
0"
#15000
1"
#20000
0"
#25000
1"
#26000
1#
#30000
0"
#35000
b1 !
b1 $
1"
#40000
0"
#45000
b10 !
b10 $
1"
#50000
0"
#55000
b11 !
b11 $
1"
#60000
0"
#65000
b100 !
b100 $
1"
#70000
0"
#75000
b101 !
b101 $
1"
#80000
0"
#85000
b110 !
b110 $
1"
#90000
0"
#95000
b111 !
b111 $
1"
#100000
0"
#105000
b1000 !
b1000 $
1"
#110000
0"
#115000
b1001 !
b1001 $
1"
#120000
0"
#125000
b1010 !
b1010 $
1"
#130000
0"
#135000
b1011 !
b1011 $
1"
#140000
0"
#145000
b1100 !
b1100 $
1"
#150000
0"
#155000
b1101 !
b1101 $
1"
#160000
0"
#165000
b1110 !
b1110 $
1"
#170000
0"
#175000
b1111 !
b1111 $
1"
#180000
0"
#185000
b10000 !
b10000 $
1"
#190000
0"
#195000
b10001 !
b10001 $
1"
#200000
0"
#205000
b10010 !
b10010 $
1"
#210000
0"
#215000
b10011 !
b10011 $
1"
#220000
0"
#225000
b10100 !
b10100 $
1"
#226000
b0 !
b0 $
0#
#230000
0"
#235000
1"
#240000
0"
#245000
1"
#246000
1#
#250000
0"
#255000
b1 !
b1 $
1"
#260000
0"
#265000
b10 !
b10 $
1"
#270000
0"
#275000
b11 !
b11 $
1"
#280000
0"
#285000
b100 !
b100 $
1"
#290000
0"
#295000
b101 !
b101 $
1"
#300000
0"
#305000
b110 !
b110 $
1"
#310000
0"
#315000
b111 !
b111 $
1"
#320000
0"
#325000
b1000 !
b1000 $
1"
#330000
0"
#335000
b1001 !
b1001 $
1"
#340000
0"
#345000
b1010 !
b1010 $
1"
